{
  "ver": 1,
  "layers": [
    {
      "layer-name": "audio2",
      "data": "unbuilt\\custom\\sfx\\default\\choppan\\audio2-0.dat"
    },
    {
      "layer-name": "audio2",
      "data": "unbuilt\\custom\\sfx\\default\\choppan\\audio2-1.dat"
    },
    {
      "layer-name": "audio2",
      "data": "unbuilt\\custom\\sfx\\default\\choppan\\audio2-2.dat"
    },
    {
      "layer-name": "audio2",
      "data": "unbuilt\\custom\\sfx\\default\\choppan\\audio2-3.dat"
    },
    {
      "layer-name": "audio2",
      "data": "unbuilt\\custom\\sfx\\default\\choppan\\audio2-4.dat"
    }
  ]
}